<system>
	<name>CoRoT-7</name>
	<contributors>
		<contributor commits="4" email="hanno@hanno-rein.de">Hanno Rein</contributor>
		<contributor commits="3" email="ryanjvarley@gmail.com">Ryan Varley</contributor>
		<contributor commits="2" email="ma.martinod@free.fr">marc-antoine</contributor>
		<contributor commits="2" email="marc-antoine.martinod@ens-cachan.fr">marc-antoine martinod</contributor>
	</contributors>
	<links>
		<link>http://phl.upr.edu/projects/habitable-exoplanets-catalog/data/database</link>
		<link>http://exoplanetarchive.ipac.caltech.edu/cgi-bin/ExoTables/nph-exotbls?dataset=planets</link>
		<link>https://github.com/ryanvarley/open_exoplanet_catalogue_advanced/issues/2</link>
		<link>http://simbad.u-strasbg.fr/simbad/sim-basic?Ident=corot-7&amp;submit=SIMBAD+search</link>
		<link>http://dx.doi.org/10.1051/0004-6361/200913096</link>
	</links>
</system>
