<system>
	<name>Gliese 86</name>
	<contributors>
		<contributor email="ajtribick@googlemail.com" commits="2">Andrew Tribick</contributor>
		<contributor email="hanno@hanno-rein.de" commits="7">Hanno Rein</contributor>
		<contributor email="marc-antoine.martinod@ens-cachan.fr" commits="1">Marc-Antoine Martinod</contributor>
		<contributor email="Tobias_Mueller@twam.info" commits="2">Tobias Mueller</contributor>
	</contributors>
	<links>
		<link>http://dx.doi.org/10.1093/mnras/sts677</link>
		<link>http://cdsads.u-strasbg.fr/abs/2006ApJ...646..505B</link>
		<link>http://cdsads.u-strasbg.fr/abs/2013MNRAS.430..652F</link>
		<link>http://phl.upr.edu/projects/habitable-exoplanets-catalog/data/database</link>
		<link>http://dx.doi.org/10.1086/591785</link>
		<link>http://dx.doi.org/10.1088/0004-637X/694/2/1085</link>
	</links>
</system>
